Metadata-Version: 1.2
Name: foamyguy-test-actions-deploy
Version: 0.0.9.dev1
Summary: Testing actions and pypi releasing
Home-page: https://github.com/FoamyGuy/test_actions_deploy
Author-email: foamyguy@gmail.com
Maintainer: Tim Cocks
Maintainer-email: foamyguy@gmail.com
License: MIT
Platform: UNKNOWN
